[
  {
    "match_id": "5101860",
    "fecha": "2026-04-25",
    "jornada": 17,
    "local": "Pachuca",
    "visita": "Pumas",
    "torneo": "Liga MX Clausura 2026",
    "elo_local": 1584.98,
    "elo_visita": 1631.94,
    "corners": {
      "over_8.5": 0.58,
      "under_8.5": 0.42,
      "over_9.5": 0.448,
      "under_9.5": 0.552,
      "over_10.5": 0.327,
      "under_10.5": 0.673,
      "lambda_total": 9.27,
      "lambda_local": 5.33,
      "lambda_visita": 3.94,
      "notes": [
        "Fase regular_late: ×1.12 tarjetas",
        "Cancha en altura (Pachuca): ×0.90 corners visitante"
      ]
    },
    "tarjetas": {
      "over_3.5": 0.695,
      "under_3.5": null,
      "over_4.5": 0.511,
      "under_4.5": 0.489,
      "over_5.5": 0.337,
      "under_5.5": 0.663,
      "lambda_total": 4.73,
      "cr_local": 2.61,
      "cr_visita": 2.12,
      "rival_bonus": 0.0
    },
    "btts": {
      "btts_si": 0.616,
      "btts_no": 0.384,
      "over_1.5": 0.825,
      "over_2.5": 0.592,
      "under_2.5": 0.408,
      "btts_over_2.5": 0.496,
      "lambda_local": 1.783,
      "lambda_visita": 1.289
    },
    "value_bets": [],
    "errors": []
  },
  {
    "match_id": "5101861",
    "fecha": "2026-04-25",
    "jornada": 17,
    "local": "Tigres",
    "visita": "Mazatlan FC",
    "torneo": "Liga MX Clausura 2026",
    "elo_local": 1558.0,
    "elo_visita": 1500.0,
    "corners": {
      "over_8.5": 0.702,
      "under_8.5": 0.298,
      "over_9.5": 0.582,
      "under_9.5": 0.418,
      "over_10.5": 0.457,
      "under_10.5": 0.543,
      "lambda_total": 10.32,
      "lambda_local": 6.12,
      "lambda_visita": 4.2,
      "notes": [
        "Fase regular_late: ×1.12 tarjetas"
      ]
    },
    "tarjetas": {
      "over_3.5": 0.741,
      "under_3.5": null,
      "over_4.5": 0.567,
      "under_4.5": 0.433,
      "over_5.5": 0.392,
      "under_5.5": 0.608,
      "lambda_total": 5.05,
      "cr_local": 3.07,
      "cr_visita": 1.97,
      "rival_bonus": 0.0
    },
    "btts": {
      "btts_si": 0.587,
      "btts_no": 0.413,
      "over_1.5": 0.805,
      "over_2.5": 0.562,
      "under_2.5": 0.438,
      "btts_over_2.5": 0.463,
      "lambda_local": 1.754,
      "lambda_visita": 1.181
    },
    "value_bets": [],
    "errors": []
  },
  {
    "match_id": "5101863",
    "fecha": "2026-04-26",
    "jornada": 17,
    "local": "Toluca",
    "visita": "Leon",
    "torneo": "Liga MX Clausura 2026",
    "elo_local": 1609.92,
    "elo_visita": 1458.39,
    "corners": {
      "over_8.5": 0.589,
      "under_8.5": 0.411,
      "over_9.5": 0.458,
      "under_9.5": 0.542,
      "over_10.5": 0.336,
      "under_10.5": 0.664,
      "lambda_total": 9.35,
      "lambda_local": 5.63,
      "lambda_visita": 3.71,
      "notes": [
        "Fase regular_late: ×1.12 tarjetas",
        "Cancha en altura (Toluca): ×0.88 corners visitante"
      ]
    },
    "tarjetas": {
      "over_3.5": 0.794,
      "under_3.5": null,
      "over_4.5": 0.636,
      "under_4.5": 0.364,
      "over_5.5": 0.464,
      "under_5.5": 0.536,
      "lambda_total": 5.46,
      "cr_local": 2.8,
      "cr_visita": 2.66,
      "rival_bonus": 0.0
    },
    "btts": {
      "btts_si": 0.585,
      "btts_no": 0.415,
      "over_1.5": 0.808,
      "over_2.5": 0.567,
      "under_2.5": 0.433,
      "btts_over_2.5": 0.463,
      "lambda_local": 1.81,
      "lambda_visita": 1.147
    },
    "value_bets": [],
    "errors": []
  },
  {
    "match_id": "5101862",
    "fecha": "2026-04-26",
    "jornada": 17,
    "local": "Chivas",
    "visita": "Tijuana",
    "torneo": "Liga MX Clausura 2026",
    "elo_local": 1626.77,
    "elo_visita": 1542.54,
    "corners": {
      "over_8.5": 0.275,
      "under_8.5": 0.725,
      "over_9.5": 0.173,
      "under_9.5": 0.827,
      "over_10.5": 0.101,
      "under_10.5": 0.899,
      "lambda_total": 7.03,
      "lambda_local": 4.18,
      "lambda_visita": 2.85,
      "notes": [
        "Fase regular_late: ×1.12 tarjetas"
      ]
    },
    "tarjetas": {
      "over_3.5": 0.789,
      "under_3.5": null,
      "over_4.5": 0.63,
      "under_4.5": 0.37,
      "over_5.5": 0.458,
      "under_5.5": 0.542,
      "lambda_total": 5.42,
      "cr_local": 2.94,
      "cr_visita": 2.49,
      "rival_bonus": 0.0
    },
    "btts": {
      "btts_si": 0.604,
      "btts_no": 0.396,
      "over_1.5": 0.821,
      "over_2.5": 0.586,
      "under_2.5": 0.414,
      "btts_over_2.5": 0.485,
      "lambda_local": 1.829,
      "lambda_visita": 1.216
    },
    "value_bets": [],
    "errors": []
  },
  {
    "match_id": "5101865",
    "fecha": "2026-04-26",
    "jornada": 17,
    "local": "FC Juarez",
    "visita": "Atletico de San Luis",
    "torneo": "Liga MX Clausura 2026",
    "elo_local": 1500.0,
    "elo_visita": 1500.0,
    "corners": {
      "over_8.5": 0.412,
      "under_8.5": 0.588,
      "over_9.5": 0.288,
      "under_9.5": 0.712,
      "over_10.5": 0.188,
      "under_10.5": 0.812,
      "lambda_total": 8.03,
      "lambda_local": 4.06,
      "lambda_visita": 3.97,
      "notes": [
        "Fase regular_late: ×1.12 tarjetas"
      ]
    },
    "tarjetas": {
      "over_3.5": 0.756,
      "under_3.5": null,
      "over_4.5": 0.586,
      "under_4.5": 0.414,
      "over_5.5": 0.411,
      "under_5.5": 0.589,
      "lambda_total": 5.16,
      "cr_local": 2.57,
      "cr_visita": 2.59,
      "rival_bonus": 0.0
    },
    "btts": {
      "btts_si": 0.58,
      "btts_no": 0.42,
      "over_1.5": 0.795,
      "over_2.5": 0.547,
      "under_2.5": 0.453,
      "btts_over_2.5": 0.452,
      "lambda_local": 1.691,
      "lambda_visita": 1.181
    },
    "value_bets": [],
    "errors": []
  },
  {
    "match_id": "5101864",
    "fecha": "2026-04-26",
    "jornada": 17,
    "local": "CF America",
    "visita": "Atlas",
    "torneo": "Liga MX Clausura 2026",
    "elo_local": 1500.0,
    "elo_visita": 1437.23,
    "corners": {
      "over_8.5": 0.375,
      "under_8.5": 0.625,
      "over_9.5": 0.255,
      "under_9.5": 0.745,
      "over_10.5": 0.162,
      "under_10.5": 0.838,
      "lambda_total": 7.77,
      "lambda_local": 4.18,
      "lambda_visita": 3.58,
      "notes": [
        "Fase regular_late: ×1.12 tarjetas"
      ]
    },
    "tarjetas": {
      "over_3.5": 0.682,
      "under_3.5": null,
      "over_4.5": 0.496,
      "under_4.5": 0.504,
      "over_5.5": 0.323,
      "under_5.5": 0.677,
      "lambda_total": 4.65,
      "cr_local": 2.01,
      "cr_visita": 2.64,
      "rival_bonus": 0.0
    },
    "btts": {
      "btts_si": 0.567,
      "btts_no": 0.433,
      "over_1.5": 0.787,
      "over_2.5": 0.535,
      "under_2.5": 0.465,
      "btts_over_2.5": 0.438,
      "lambda_local": 1.691,
      "lambda_visita": 1.13
    },
    "value_bets": [],
    "errors": []
  },
  {
    "match_id": "5101866",
    "fecha": "2026-04-26",
    "jornada": 17,
    "local": "Santos Laguna",
    "visita": "Monterrey",
    "torneo": "Liga MX Clausura 2026",
    "elo_local": 1356.98,
    "elo_visita": 1472.17,
    "corners": {
      "over_8.5": 0.574,
      "under_8.5": 0.426,
      "over_9.5": 0.443,
      "under_9.5": 0.557,
      "over_10.5": 0.322,
      "under_10.5": 0.678,
      "lambda_total": 9.23,
      "lambda_local": 4.88,
      "lambda_visita": 4.35,
      "notes": [
        "Fase regular_late: ×1.12 tarjetas"
      ]
    },
    "tarjetas": {
      "over_3.5": 0.745,
      "under_3.5": null,
      "over_4.5": 0.572,
      "under_4.5": 0.428,
      "over_5.5": 0.397,
      "under_5.5": 0.603,
      "lambda_total": 5.07,
      "cr_local": 3.1,
      "cr_visita": 1.98,
      "rival_bonus": 0.0
    },
    "btts": {
      "btts_si": 0.554,
      "btts_no": 0.446,
      "over_1.5": 0.766,
      "over_2.5": 0.505,
      "under_2.5": 0.495,
      "btts_over_2.5": 0.418,
      "lambda_local": 1.535,
      "lambda_visita": 1.159
    },
    "value_bets": [],
    "errors": []
  },
  {
    "match_id": "5101867",
    "fecha": "2026-04-27",
    "jornada": 17,
    "local": "Cruz Azul",
    "visita": "Necaxa",
    "torneo": "Liga MX Clausura 2026",
    "elo_local": 1642.51,
    "elo_visita": 1439.16,
    "corners": {
      "over_8.5": 0.689,
      "under_8.5": 0.311,
      "over_9.5": 0.567,
      "under_9.5": 0.433,
      "over_10.5": 0.442,
      "under_10.5": 0.558,
      "lambda_total": 10.2,
      "lambda_local": 5.94,
      "lambda_visita": 4.26,
      "notes": [
        "Fase regular_late: ×1.12 tarjetas"
      ]
    },
    "tarjetas": {
      "over_3.5": 0.726,
      "under_3.5": null,
      "over_4.5": 0.548,
      "under_4.5": 0.452,
      "over_5.5": 0.373,
      "under_5.5": 0.627,
      "lambda_total": 4.94,
      "cr_local": 2.48,
      "cr_visita": 2.46,
      "rival_bonus": 0.0
    },
    "btts": {
      "btts_si": 0.584,
      "btts_no": 0.416,
      "over_1.5": 0.811,
      "over_2.5": 0.571,
      "under_2.5": 0.429,
      "btts_over_2.5": 0.464,
      "lambda_local": 1.846,
      "lambda_visita": 1.132
    },
    "value_bets": [],
    "errors": []
  }
]