{
  "date": "2026-04-14",
  "start": "2026-04-14T15:06:16.988985",
  "pasos": {
    "paso1": {
      "nuevos": 1,
      "terminados_antes": 125,
      "terminados_despues": 126,
      "error": null,
      "elapsed_s": 68.7
    },
    "paso2": {
      "equipos_afectados": 2,
      "registros_nuevos": 2,
      "error": null,
      "elapsed_s": 0.0
    },
    "paso3": {
      "nuevos": 0,
      "fechas_procesadas": 0,
      "error": null,
      "elapsed_s": 408.0
    },
    "paso4": {
      "selecciones_afectadas": 0,
      "nuevo_archivo": null,
      "error": null,
      "elapsed_s": 0.1
    },
    "paso5": {
      "actualizados": 0,
      "pendientes": 9,
      "aciertos": 11,
      "total_evaluados": 23,
      "error": null,
      "elapsed_s": 2.6
    },
    "paso6": {
      "predicciones_generadas": 1,
      "saltado": false,
      "error": null,
      "elapsed_s": 1.6
    },
    "paso7": {
      "committed": false,
      "pushed": false,
      "error": null
    }
  },
  "end": "2026-04-14T15:14:18.019014",
  "elapsed_s": 481.0,
  "success": true,
  "critical_failed": false,
  "noncritical_errors": []
}