{
  "torneo": "2023/2024 - Clausura",
  "season_id": 20894,
  "torneo_tipo": "Clausura",
  "year": "2023/2024",
  "tabla": [
    {
      "pos": 1,
      "equipo": "CF America",
      "equipo_id": 6576,
      "pj": 17,
      "g": 10,
      "e": 5,
      "p": 2,
      "gf": 30,
      "gc": 12,
      "pts": 35
    },
    {
      "pos": 2,
      "equipo": "Cruz Azul",
      "equipo_id": 6578,
      "pj": 17,
      "g": 10,
      "e": 3,
      "p": 4,
      "gf": 23,
      "gc": 14,
      "pts": 33
    },
    {
      "pos": 3,
      "equipo": "Toluca",
      "equipo_id": 6618,
      "pj": 17,
      "g": 9,
      "e": 5,
      "p": 3,
      "gf": 38,
      "gc": 23,
      "pts": 32
    },
    {
      "pos": 4,
      "equipo": "Monterrey",
      "equipo_id": 7849,
      "pj": 17,
      "g": 9,
      "e": 5,
      "p": 3,
      "gf": 32,
      "gc": 19,
      "pts": 32
    },
    {
      "pos": 5,
      "equipo": "Tigres",
      "equipo_id": 8561,
      "pj": 17,
      "g": 9,
      "e": 4,
      "p": 4,
      "gf": 34,
      "gc": 23,
      "pts": 31
    },
    {
      "pos": 6,
      "equipo": "Chivas",
      "equipo_id": 7807,
      "pj": 17,
      "g": 9,
      "e": 4,
      "p": 4,
      "gf": 24,
      "gc": 17,
      "pts": 31
    },
    {
      "pos": 7,
      "equipo": "Pachuca",
      "equipo_id": 7848,
      "pj": 17,
      "g": 9,
      "e": 2,
      "p": 6,
      "gf": 34,
      "gc": 27,
      "pts": 29
    },
    {
      "pos": 8,
      "equipo": "Pumas",
      "equipo_id": 1946,
      "pj": 17,
      "g": 7,
      "e": 6,
      "p": 4,
      "gf": 27,
      "gc": 22,
      "pts": 27
    },
    {
      "pos": 9,
      "equipo": "Necaxa",
      "equipo_id": 1842,
      "pj": 17,
      "g": 7,
      "e": 6,
      "p": 4,
      "gf": 30,
      "gc": 29,
      "pts": 27
    },
    {
      "pos": 10,
      "equipo": "Queretaro FC",
      "equipo_id": 1943,
      "pj": 17,
      "g": 6,
      "e": 6,
      "p": 5,
      "gf": 22,
      "gc": 21,
      "pts": 24
    },
    {
      "pos": 11,
      "equipo": "Leon",
      "equipo_id": 1841,
      "pj": 17,
      "g": 7,
      "e": 3,
      "p": 7,
      "gf": 23,
      "gc": 25,
      "pts": 24
    },
    {
      "pos": 12,
      "equipo": "FC Juarez",
      "equipo_id": 649424,
      "pj": 17,
      "g": 4,
      "e": 4,
      "p": 9,
      "gf": 19,
      "gc": 26,
      "pts": 16
    },
    {
      "pos": 13,
      "equipo": "Atletico de San Luis",
      "equipo_id": 6358,
      "pj": 17,
      "g": 5,
      "e": 1,
      "p": 11,
      "gf": 25,
      "gc": 35,
      "pts": 16
    },
    {
      "pos": 14,
      "equipo": "Mazatlan FC",
      "equipo_id": 1170234,
      "pj": 17,
      "g": 4,
      "e": 4,
      "p": 9,
      "gf": 21,
      "gc": 32,
      "pts": 16
    },
    {
      "pos": 15,
      "equipo": "Santos Laguna",
      "equipo_id": 7857,
      "pj": 17,
      "g": 4,
      "e": 3,
      "p": 10,
      "gf": 15,
      "gc": 28,
      "pts": 15
    },
    {
      "pos": 16,
      "equipo": "Tijuana",
      "equipo_id": 162418,
      "pj": 17,
      "g": 2,
      "e": 8,
      "p": 7,
      "gf": 21,
      "gc": 30,
      "pts": 14
    },
    {
      "pos": 17,
      "equipo": "Atlas",
      "equipo_id": 6577,
      "pj": 17,
      "g": 3,
      "e": 5,
      "p": 9,
      "gf": 21,
      "gc": 31,
      "pts": 14
    },
    {
      "pos": 18,
      "equipo": "Puebla",
      "equipo_id": 7847,
      "pj": 17,
      "g": 1,
      "e": 2,
      "p": 14,
      "gf": 18,
      "gc": 43,
      "pts": 5
    }
  ],
  "partidos": [
    {
      "id": "4384303",
      "fecha": "2024-01-13T01:00:00Z",
      "jornada": "1",
      "local": "Queretaro FC",
      "local_id": "1943",
      "visitante": "Toluca",
      "visitante_id": "6618",
      "goles_local": 2,
      "goles_visit": 2,
      "score": "2 - 2",
      "terminado": true
    },
    {
      "id": "4384305",
      "fecha": "2024-01-13T03:00:00Z",
      "jornada": "1",
      "local": "Mazatlan FC",
      "local_id": "1170234",
      "visitante": "Atletico de San Luis",
      "visitante_id": "6358",
      "goles_local": 0,
      "goles_visit": 1,
      "score": "0 - 1",
      "terminado": true
    },
    {
      "id": "4384299",
      "fecha": "2024-01-14T01:00:00Z",
      "jornada": "1",
      "local": "Cruz Azul",
      "local_id": "6578",
      "visitante": "Pachuca",
      "visitante_id": "7848",
      "goles_local": 0,
      "goles_visit": 1,
      "score": "0 - 1",
      "terminado": true
    },
    {
      "id": "4384300",
      "fecha": "2024-01-14T01:05:00Z",
      "jornada": "1",
      "local": "Chivas",
      "local_id": "7807",
      "visitante": "Santos Laguna",
      "visitante_id": "7857",
      "goles_local": 1,
      "goles_visit": 1,
      "score": "1 - 1",
      "terminado": true
    },
    {
      "id": "4384297",
      "fecha": "2024-01-14T03:00:00Z",
      "jornada": "1",
      "local": "Monterrey",
      "local_id": "7849",
      "visitante": "Puebla",
      "visitante_id": "7847",
      "goles_local": 2,
      "goles_visit": 0,
      "score": "2 - 0",
      "terminado": true
    },
    {
      "id": "4384301",
      "fecha": "2024-01-14T03:00:00Z",
      "jornada": "1",
      "local": "Tijuana",
      "local_id": "162418",
      "visitante": "CF America",
      "visitante_id": "6576",
      "goles_local": 0,
      "goles_visit": 2,
      "score": "0 - 2",
      "terminado": true
    },
    {
      "id": "4384298",
      "fecha": "2024-01-14T18:00:00Z",
      "jornada": "1",
      "local": "Pumas",
      "local_id": "1946",
      "visitante": "FC Juarez",
      "visitante_id": "649424",
      "goles_local": 1,
      "goles_visit": 0,
      "score": "1 - 0",
      "terminado": true
    },
    {
      "id": "4384304",
      "fecha": "2024-01-15T00:00:00Z",
      "jornada": "1",
      "local": "Necaxa",
      "local_id": "1842",
      "visitante": "Atlas",
      "visitante_id": "6577",
      "goles_local": 2,
      "goles_visit": 1,
      "score": "2 - 1",
      "terminado": true
    },
    {
      "id": "4384302",
      "fecha": "2024-01-18T01:00:00Z",
      "jornada": "1",
      "local": "Leon",
      "local_id": "1841",
      "visitante": "Tigres",
      "visitante_id": "8561",
      "goles_local": 1,
      "goles_visit": 2,
      "score": "1 - 2",
      "terminado": true
    },
    {
      "id": "4384403",
      "fecha": "2024-01-20T01:00:00Z",
      "jornada": "2",
      "local": "Puebla",
      "local_id": "7847",
      "visitante": "Necaxa",
      "visitante_id": "1842",
      "goles_local": 1,
      "goles_visit": 2,
      "score": "1 - 2",
      "terminado": true
    },
    {
      "id": "4384393",
      "fecha": "2024-01-20T03:00:00Z",
      "jornada": "2",
      "local": "Atletico de San Luis",
      "local_id": "6358",
      "visitante": "Pumas",
      "visitante_id": "1946",
      "goles_local": 3,
      "goles_visit": 1,
      "score": "3 - 1",
      "terminado": true
    },
    {
      "id": "4384394",
      "fecha": "2024-01-20T03:10:00Z",
      "jornada": "2",
      "local": "FC Juarez",
      "local_id": "649424",
      "visitante": "Cruz Azul",
      "visitante_id": "6578",
      "goles_local": 0,
      "goles_visit": 0,
      "score": "0 - 0",
      "terminado": true
    },
    {
      "id": "4384395",
      "fecha": "2024-01-20T23:00:00Z",
      "jornada": "2",
      "local": "Toluca",
      "local_id": "6618",
      "visitante": "Mazatlan FC",
      "visitante_id": "1170234",
      "goles_local": 4,
      "goles_visit": 1,
      "score": "4 - 1",
      "terminado": true
    },
    {
      "id": "4384396",
      "fecha": "2024-01-21T01:05:00Z",
      "jornada": "2",
      "local": "CF America",
      "local_id": "6576",
      "visitante": "Queretaro FC",
      "visitante_id": "1943",
      "goles_local": 2,
      "goles_visit": 0,
      "score": "2 - 0",
      "terminado": true
    },
    {
      "id": "4384397",
      "fecha": "2024-01-21T03:10:00Z",
      "jornada": "2",
      "local": "Atlas",
      "local_id": "6577",
      "visitante": "Tijuana",
      "visitante_id": "162418",
      "goles_local": 0,
      "goles_visit": 0,
      "score": "0 - 0",
      "terminado": true
    },
    {
      "id": "4384398",
      "fecha": "2024-01-22T00:00:00Z",
      "jornada": "2",
      "local": "Tigres",
      "local_id": "8561",
      "visitante": "Chivas",
      "visitante_id": "7807",
      "goles_local": 1,
      "goles_visit": 0,
      "score": "1 - 0",
      "terminado": true
    },
    {
      "id": "4384399",
      "fecha": "2024-01-22T02:05:00Z",
      "jornada": "2",
      "local": "Santos Laguna",
      "local_id": "7857",
      "visitante": "Monterrey",
      "visitante_id": "7849",
      "goles_local": 0,
      "goles_visit": 2,
      "score": "0 - 2",
      "terminado": true
    },
    {
      "id": "4384410",
      "fecha": "2024-01-25T01:00:00Z",
      "jornada": "4",
      "local": "Atletico de San Luis",
      "local_id": "6358",
      "visitante": "Tigres",
      "visitante_id": "8561",
      "goles_local": 1,
      "goles_visit": 2,
      "score": "1 - 2",
      "terminado": true
    },
    {
      "id": "4384411",
      "fecha": "2024-01-25T01:00:00Z",
      "jornada": "4",
      "local": "Monterrey",
      "local_id": "7849",
      "visitante": "Queretaro FC",
      "visitante_id": "1943",
      "goles_local": 1,
      "goles_visit": 1,
      "score": "1 - 1",
      "terminado": true
    },
    {
      "id": "4384412",
      "fecha": "2024-01-25T03:05:00Z",
      "jornada": "4",
      "local": "FC Juarez",
      "local_id": "649424",
      "visitante": "CF America",
      "visitante_id": "6576",
      "goles_local": 0,
      "goles_visit": 2,
      "score": "0 - 2",
      "terminado": true
    },
    {
      "id": "4384401",
      "fecha": "2024-01-27T01:00:00Z",
      "jornada": "3",
      "local": "Puebla",
      "local_id": "7847",
      "visitante": "Toluca",
      "visitante_id": "6618",
      "goles_local": 1,
      "goles_visit": 1,
      "score": "1 - 1",
      "terminado": true
    },
    {
      "id": "4384402",
      "fecha": "2024-01-27T03:00:00Z",
      "jornada": "3",
      "local": "Tijuana",
      "local_id": "162418",
      "visitante": "Chivas",
      "visitante_id": "7807",
      "goles_local": 1,
      "goles_visit": 1,
      "score": "1 - 1",
      "terminado": true
    },
    {
      "id": "4384392",
      "fecha": "2024-01-27T23:00:00Z",
      "jornada": "3",
      "local": "Cruz Azul",
      "local_id": "6578",
      "visitante": "Mazatlan FC",
      "visitante_id": "1170234",
      "goles_local": 2,
      "goles_visit": 1,
      "score": "2 - 1",
      "terminado": true
    },
    {
      "id": "4384404",
      "fecha": "2024-01-27T23:00:00Z",
      "jornada": "3",
      "local": "Leon",
      "local_id": "1841",
      "visitante": "Santos Laguna",
      "visitante_id": "7857",
      "goles_local": 3,
      "goles_visit": 2,
      "score": "3 - 2",
      "terminado": true
    },
    {
      "id": "4384405",
      "fecha": "2024-01-28T01:00:00Z",
      "jornada": "3",
      "local": "Monterrey",
      "local_id": "7849",
      "visitante": "Atletico de San Luis",
      "visitante_id": "6358",
      "goles_local": 3,
      "goles_visit": 1,
      "score": "3 - 1",
      "terminado": true
    },
    {
      "id": "4384406",
      "fecha": "2024-01-28T03:05:00Z",
      "jornada": "3",
      "local": "Necaxa",
      "local_id": "1842",
      "visitante": "CF America",
      "visitante_id": "6576",
      "goles_local": 0,
      "goles_visit": 0,
      "score": "0 - 0",
      "terminado": true
    },
    {
      "id": "4384408",
      "fecha": "2024-01-28T23:15:00Z",
      "jornada": "3",
      "local": "Pumas",
      "local_id": "1946",
      "visitante": "Pachuca",
      "visitante_id": "7848",
      "goles_local": 3,
      "goles_visit": 1,
      "score": "3 - 1",
      "terminado": true
    },
    {
      "id": "4384407",
      "fecha": "2024-01-29T01:00:00Z",
      "jornada": "3",
      "local": "Atlas",
      "local_id": "6577",
      "visitante": "FC Juarez",
      "visitante_id": "649424",
      "goles_local": 2,
      "goles_visit": 1,
      "score": "2 - 1",
      "terminado": true
    },
    {
      "id": "4384409",
      "fecha": "2024-01-29T03:00:00Z",
      "jornada": "3",
      "local": "Queretaro FC",
      "local_id": "1943",
      "visitante": "Tigres",
      "visitante_id": "8561",
      "goles_local": 1,
      "goles_visit": 1,
      "score": "1 - 1",
      "terminado": true
    },
    {
      "id": "4384381",
      "fecha": "2024-01-31T01:00:00Z",
      "jornada": "4",
      "local": "Cruz Azul",
      "local_id": "6578",
      "visitante": "Tijuana",
      "visitante_id": "162418",
      "goles_local": 1,
      "goles_visit": 0,
      "score": "1 - 0",
      "terminado": true
    },
    {
      "id": "4384371",
      "fecha": "2024-01-31T01:00:00Z",
      "jornada": "4",
      "local": "Mazatlan FC",
      "local_id": "1170234",
      "visitante": "Leon",
      "visitante_id": "1841",
      "goles_local": 2,
      "goles_visit": 2,
      "score": "2 - 2",
      "terminado": true
    },
    {
      "id": "4384374",
      "fecha": "2024-01-31T03:00:00Z",
      "jornada": "4",
      "local": "Santos Laguna",
      "local_id": "7857",
      "visitante": "Puebla",
      "visitante_id": "7847",
      "goles_local": 3,
      "goles_visit": 0,
      "score": "3 - 0",
      "terminado": true
    },
    {
      "id": "4384372",
      "fecha": "2024-01-31T03:05:00Z",
      "jornada": "4",
      "local": "Chivas",
      "local_id": "7807",
      "visitante": "Toluca",
      "visitante_id": "6618",
      "goles_local": 3,
      "goles_visit": 2,
      "score": "3 - 2",
      "terminado": true
    },
    {
      "id": "4384373",
      "fecha": "2024-02-01T01:00:00Z",
      "jornada": "4",
      "local": "Pachuca",
      "local_id": "7848",
      "visitante": "Atlas",
      "visitante_id": "6577",
      "goles_local": 4,
      "goles_visit": 3,
      "score": "4 - 3",
      "terminado": true
    },
    {
      "id": "4384375",
      "fecha": "2024-02-01T03:00:00Z",
      "jornada": "4",
      "local": "Pumas",
      "local_id": "1946",
      "visitante": "Necaxa",
      "visitante_id": "1842",
      "goles_local": 2,
      "goles_visit": 2,
      "score": "2 - 2",
      "terminado": true
    },
    {
      "id": "4384376",
      "fecha": "2024-02-03T01:00:00Z",
      "jornada": "5",
      "local": "Queretaro FC",
      "local_id": "1943",
      "visitante": "Cruz Azul",
      "visitante_id": "6578",
      "goles_local": 1,
      "goles_visit": 3,
      "score": "1 - 3",
      "terminado": true
    },
    {
      "id": "4384377",
      "fecha": "2024-02-03T03:00:00Z",
      "jornada": "5",
      "local": "Puebla",
      "local_id": "7847",
      "visitante": "Mazatlan FC",
      "visitante_id": "1170234",
      "goles_local": 3,
      "goles_visit": 2,
      "score": "3 - 2",
      "terminado": true
    },
    {
      "id": "4384378",
      "fecha": "2024-02-03T23:00:00Z",
      "jornada": "5",
      "local": "Toluca",
      "local_id": "6618",
      "visitante": "Leon",
      "visitante_id": "1841",
      "goles_local": 4,
      "goles_visit": 1,
      "score": "4 - 1",
      "terminado": true
    },
    {
      "id": "4384379",
      "fecha": "2024-02-03T23:06:00Z",
      "jornada": "5",
      "local": "FC Juarez",
      "local_id": "649424",
      "visitante": "Necaxa",
      "visitante_id": "1842",
      "goles_local": 2,
      "goles_visit": 2,
      "score": "2 - 2",
      "terminado": true
    },
    {
      "id": "4384370",
      "fecha": "2024-02-04T01:05:00Z",
      "jornada": "5",
      "local": "Tigres",
      "local_id": "8561",
      "visitante": "Pumas",
      "visitante_id": "1946",
      "goles_local": 2,
      "goles_visit": 2,
      "score": "2 - 2",
      "terminado": true
    },
    {
      "id": "4384380",
      "fecha": "2024-02-04T01:10:00Z",
      "jornada": "5",
      "local": "Pachuca",
      "local_id": "7848",
      "visitante": "Tijuana",
      "visitante_id": "162418",
      "goles_local": 3,
      "goles_visit": 2,
      "score": "3 - 2",
      "terminado": true
    },
    {
      "id": "4384382",
      "fecha": "2024-02-04T03:10:00Z",
      "jornada": "5",
      "local": "CF America",
      "local_id": "6576",
      "visitante": "Monterrey",
      "visitante_id": "7849",
      "goles_local": 1,
      "goles_visit": 1,
      "score": "1 - 1",
      "terminado": true
    },
    {
      "id": "4384383",
      "fecha": "2024-02-05T00:00:00Z",
      "jornada": "5",
      "local": "Atlas",
      "local_id": "6577",
      "visitante": "Santos Laguna",
      "visitante_id": "7857",
      "goles_local": 3,
      "goles_visit": 0,
      "score": "3 - 0",
      "terminado": true
    },
    {
      "id": "4384509",
      "fecha": "2024-02-05T01:00:00Z",
      "jornada": "5",
      "local": "Atletico de San Luis",
      "local_id": "6358",
      "visitante": "Chivas",
      "visitante_id": "7807",
      "goles_local": 0,
      "goles_visit": 2,
      "score": "0 - 2",
      "terminado": true
    },
    {
      "id": "4384400",
      "fecha": "2024-02-08T03:00:00Z",
      "jornada": "2",
      "local": "Pachuca",
      "local_id": "7848",
      "visitante": "Leon",
      "visitante_id": "1841",
      "goles_local": 3,
      "goles_visit": 2,
      "score": "3 - 2",
      "terminado": true
    },
    {
      "id": "4384384",
      "fecha": "2024-02-10T01:00:00Z",
      "jornada": "6",
      "local": "Mazatlan FC",
      "local_id": "1170234",
      "visitante": "Atlas",
      "visitante_id": "6577",
      "goles_local": 2,
      "goles_visit": 0,
      "score": "2 - 0",
      "terminado": true
    },
    {
      "id": "4384385",
      "fecha": "2024-02-10T03:10:00Z",
      "jornada": "6",
      "local": "Tijuana",
      "local_id": "162418",
      "visitante": "Queretaro FC",
      "visitante_id": "1943",
      "goles_local": 1,
      "goles_visit": 1,
      "score": "1 - 1",
      "terminado": true
    },
    {
      "id": "4384386",
      "fecha": "2024-02-10T23:00:00Z",
      "jornada": "6",
      "local": "Necaxa",
      "local_id": "1842",
      "visitante": "Toluca",
      "visitante_id": "6618",
      "goles_local": 3,
      "goles_visit": 3,
      "score": "3 - 3",
      "terminado": true
    },
    {
      "id": "4384387",
      "fecha": "2024-02-10T23:05:00Z",
      "jornada": "6",
      "local": "Chivas",
      "local_id": "7807",
      "visitante": "FC Juarez",
      "visitante_id": "649424",
      "goles_local": 2,
      "goles_visit": 1,
      "score": "2 - 1",
      "terminado": true
    },
    {
      "id": "4384389",
      "fecha": "2024-02-11T01:00:00Z",
      "jornada": "6",
      "local": "Leon",
      "local_id": "1841",
      "visitante": "CF America",
      "visitante_id": "6576",
      "goles_local": 0,
      "goles_visit": 1,
      "score": "0 - 1",
      "terminado": true
    },
    {
      "id": "4384388",
      "fecha": "2024-02-11T01:05:00Z",
      "jornada": "6",
      "local": "Cruz Azul",
      "local_id": "6578",
      "visitante": "Atletico de San Luis",
      "visitante_id": "6358",
      "goles_local": 3,
      "goles_visit": 0,
      "score": "3 - 0",
      "terminado": true
    },
    {
      "id": "4384390",
      "fecha": "2024-02-11T03:10:00Z",
      "jornada": "6",
      "local": "Monterrey",
      "local_id": "7849",
      "visitante": "Pachuca",
      "visitante_id": "7848",
      "goles_local": 3,
      "goles_visit": 2,
      "score": "3 - 2",
      "terminado": true
    },
    {
      "id": "4384391",
      "fecha": "2024-02-11T03:10:00Z",
      "jornada": "6",
      "local": "Santos Laguna",
      "local_id": "7857",
      "visitante": "Tigres",
      "visitante_id": "8561",
      "goles_local": 0,
      "goles_visit": 3,
      "score": "0 - 3",
      "terminado": true
    },
    {
      "id": "4384446",
      "fecha": "2024-02-11T18:00:00Z",
      "jornada": "6",
      "local": "Pumas",
      "local_id": "1946",
      "visitante": "Puebla",
      "visitante_id": "7847",
      "goles_local": 3,
      "goles_visit": 0,
      "score": "3 - 0",
      "terminado": true
    },
    {
      "id": "4384453",
      "fecha": "2024-02-15T03:00:00Z",
      "jornada": "9",
      "local": "Atlas",
      "local_id": "6577",
      "visitante": "Pumas",
      "visitante_id": "1946",
      "goles_local": 0,
      "goles_visit": 0,
      "score": "0 - 0",
      "terminado": true
    },
    {
      "id": "4384436",
      "fecha": "2024-02-17T01:00:00Z",
      "jornada": "7",
      "local": "Queretaro FC",
      "local_id": "1943",
      "visitante": "Necaxa",
      "visitante_id": "1842",
      "goles_local": 1,
      "goles_visit": 1,
      "score": "1 - 1",
      "terminado": true
    },
    {
      "id": "4384437",
      "fecha": "2024-02-17T03:00:00Z",
      "jornada": "7",
      "local": "Mazatlan FC",
      "local_id": "1170234",
      "visitante": "Chivas",
      "visitante_id": "7807",
      "goles_local": 2,
      "goles_visit": 2,
      "score": "2 - 2",
      "terminado": true
    },
    {
      "id": "4384439",
      "fecha": "2024-02-17T23:00:00Z",
      "jornada": "7",
      "local": "Atletico de San Luis",
      "local_id": "6358",
      "visitante": "Tijuana",
      "visitante_id": "162418",
      "goles_local": 3,
      "goles_visit": 3,
      "score": "3 - 3",
      "terminado": true
    },
    {
      "id": "4384440",
      "fecha": "2024-02-18T01:00:00Z",
      "jornada": "7",
      "local": "Pachuca",
      "local_id": "7848",
      "visitante": "CF America",
      "visitante_id": "6576",
      "goles_local": 2,
      "goles_visit": 1,
      "score": "2 - 1",
      "terminado": true
    },
    {
      "id": "4384441",
      "fecha": "2024-02-18T03:05:00Z",
      "jornada": "7",
      "local": "Cruz Azul",
      "local_id": "6578",
      "visitante": "Tigres",
      "visitante_id": "8561",
      "goles_local": 1,
      "goles_visit": 0,
      "score": "1 - 0",
      "terminado": true
    },
    {
      "id": "4384442",
      "fecha": "2024-02-18T22:00:00Z",
      "jornada": "7",
      "local": "Atlas",
      "local_id": "6577",
      "visitante": "Leon",
      "visitante_id": "1841",
      "goles_local": 0,
      "goles_visit": 1,
      "score": "0 - 1",
      "terminado": true
    },
    {
      "id": "4384443",
      "fecha": "2024-02-19T00:05:00Z",
      "jornada": "7",
      "local": "Pumas",
      "local_id": "1946",
      "visitante": "Santos Laguna",
      "visitante_id": "7857",
      "goles_local": 3,
      "goles_visit": 0,
      "score": "3 - 0",
      "terminado": true
    },
    {
      "id": "4384510",
      "fecha": "2024-02-19T02:10:00Z",
      "jornada": "7",
      "local": "Monterrey",
      "local_id": "7849",
      "visitante": "Toluca",
      "visitante_id": "6618",
      "goles_local": 0,
      "goles_visit": 0,
      "score": "0 - 0",
      "terminado": true
    },
    {
      "id": "4384454",
      "fecha": "2024-02-21T01:00:00Z",
      "jornada": "9",
      "local": "Puebla",
      "local_id": "7847",
      "visitante": "Pachuca",
      "visitante_id": "7848",
      "goles_local": 1,
      "goles_visit": 4,
      "score": "1 - 4",
      "terminado": true
    },
    {
      "id": "4384511",
      "fecha": "2024-02-21T03:00:00Z",
      "jornada": "9",
      "local": "Necaxa",
      "local_id": "1842",
      "visitante": "Chivas",
      "visitante_id": "7807",
      "goles_local": 1,
      "goles_visit": 0,
      "score": "1 - 0",
      "terminado": true
    },
    {
      "id": "4384512",
      "fecha": "2024-02-22T01:00:00Z",
      "jornada": "9",
      "local": "Toluca",
      "local_id": "6618",
      "visitante": "Santos Laguna",
      "visitante_id": "7857",
      "goles_local": 1,
      "goles_visit": 0,
      "score": "1 - 0",
      "terminado": true
    },
    {
      "id": "4384513",
      "fecha": "2024-02-22T03:00:00Z",
      "jornada": "9",
      "local": "CF America",
      "local_id": "6576",
      "visitante": "Mazatlan FC",
      "visitante_id": "1170234",
      "goles_local": 2,
      "goles_visit": 2,
      "score": "2 - 2",
      "terminado": true
    },
    {
      "id": "4384455",
      "fecha": "2024-02-22T03:00:00Z",
      "jornada": "9",
      "local": "Leon",
      "local_id": "1841",
      "visitante": "Cruz Azul",
      "visitante_id": "6578",
      "goles_local": 2,
      "goles_visit": 3,
      "score": "2 - 3",
      "terminado": true
    },
    {
      "id": "4384444",
      "fecha": "2024-02-24T01:00:00Z",
      "jornada": "8",
      "local": "Puebla",
      "local_id": "7847",
      "visitante": "Queretaro FC",
      "visitante_id": "1943",
      "goles_local": 0,
      "goles_visit": 2,
      "score": "0 - 2",
      "terminado": true
    },
    {
      "id": "4384435",
      "fecha": "2024-02-24T03:00:00Z",
      "jornada": "8",
      "local": "FC Juarez",
      "local_id": "649424",
      "visitante": "Monterrey",
      "visitante_id": "7849",
      "goles_local": 0,
      "goles_visit": 3,
      "score": "0 - 3",
      "terminado": true
    },
    {
      "id": "4384445",
      "fecha": "2024-02-24T03:00:00Z",
      "jornada": "8",
      "local": "Necaxa",
      "local_id": "1842",
      "visitante": "Pachuca",
      "visitante_id": "7848",
      "goles_local": 1,
      "goles_visit": 1,
      "score": "1 - 1",
      "terminado": true
    },
    {
      "id": "4384447",
      "fecha": "2024-02-24T23:00:00Z",
      "jornada": "8",
      "local": "Leon",
      "local_id": "1841",
      "visitante": "Atletico de San Luis",
      "visitante_id": "6358",
      "goles_local": 1,
      "goles_visit": 0,
      "score": "1 - 0",
      "terminado": true
    },
    {
      "id": "4384449",
      "fecha": "2024-02-25T01:00:00Z",
      "jornada": "8",
      "local": "Tigres",
      "local_id": "8561",
      "visitante": "Atlas",
      "visitante_id": "6577",
      "goles_local": 1,
      "goles_visit": 1,
      "score": "1 - 1",
      "terminado": true
    },
    {
      "id": "4384448",
      "fecha": "2024-02-25T01:05:00Z",
      "jornada": "8",
      "local": "Chivas",
      "local_id": "7807",
      "visitante": "Pumas",
      "visitante_id": "1946",
      "goles_local": 3,
      "goles_visit": 1,
      "score": "3 - 1",
      "terminado": true
    },
    {
      "id": "4384450",
      "fecha": "2024-02-25T03:10:00Z",
      "jornada": "8",
      "local": "CF America",
      "local_id": "6576",
      "visitante": "Cruz Azul",
      "visitante_id": "6578",
      "goles_local": 1,
      "goles_visit": 0,
      "score": "1 - 0",
      "terminado": true
    },
    {
      "id": "4384451",
      "fecha": "2024-02-25T18:00:00Z",
      "jornada": "8",
      "local": "Toluca",
      "local_id": "6618",
      "visitante": "Tijuana",
      "visitante_id": "162418",
      "goles_local": 2,
      "goles_visit": 0,
      "score": "2 - 0",
      "terminado": true
    },
    {
      "id": "4384452",
      "fecha": "2024-02-26T00:00:00Z",
      "jornada": "8",
      "local": "Santos Laguna",
      "local_id": "7857",
      "visitante": "Mazatlan FC",
      "visitante_id": "1170234",
      "goles_local": 1,
      "goles_visit": 0,
      "score": "1 - 0",
      "terminado": true
    },
    {
      "id": "4384424",
      "fecha": "2024-02-28T01:00:00Z",
      "jornada": "9",
      "local": "Queretaro FC",
      "local_id": "1943",
      "visitante": "Atletico de San Luis",
      "visitante_id": "6358",
      "goles_local": 4,
      "goles_visit": 1,
      "score": "4 - 1",
      "terminado": true
    },
    {
      "id": "4384414",
      "fecha": "2024-02-29T01:00:00Z",
      "jornada": "9",
      "local": "Tigres",
      "local_id": "8561",
      "visitante": "FC Juarez",
      "visitante_id": "649424",
      "goles_local": 1,
      "goles_visit": 0,
      "score": "1 - 0",
      "terminado": true
    },
    {
      "id": "4384415",
      "fecha": "2024-02-29T03:00:00Z",
      "jornada": "9",
      "local": "Tijuana",
      "local_id": "162418",
      "visitante": "Monterrey",
      "visitante_id": "7849",
      "goles_local": 1,
      "goles_visit": 1,
      "score": "1 - 1",
      "terminado": true
    },
    {
      "id": "4384417",
      "fecha": "2024-03-02T01:00:00Z",
      "jornada": "10",
      "local": "Atletico de San Luis",
      "local_id": "6358",
      "visitante": "Puebla",
      "visitante_id": "7847",
      "goles_local": 4,
      "goles_visit": 0,
      "score": "4 - 0",
      "terminado": true
    },
    {
      "id": "4384416",
      "fecha": "2024-03-02T01:00:00Z",
      "jornada": "10",
      "local": "Queretaro FC",
      "local_id": "1943",
      "visitante": "Santos Laguna",
      "visitante_id": "7857",
      "goles_local": 0,
      "goles_visit": 1,
      "score": "0 - 1",
      "terminado": true
    },
    {
      "id": "4384418",
      "fecha": "2024-03-02T03:00:00Z",
      "jornada": "10",
      "local": "Mazatlan FC",
      "local_id": "1170234",
      "visitante": "Necaxa",
      "visitante_id": "1842",
      "goles_local": 2,
      "goles_visit": 1,
      "score": "2 - 1",
      "terminado": true
    },
    {
      "id": "4384419",
      "fecha": "2024-03-02T23:00:00Z",
      "jornada": "10",
      "local": "Toluca",
      "local_id": "6618",
      "visitante": "Tigres",
      "visitante_id": "8561",
      "goles_local": 2,
      "goles_visit": 1,
      "score": "2 - 1",
      "terminado": true
    },
    {
      "id": "4384420",
      "fecha": "2024-03-03T01:00:00Z",
      "jornada": "10",
      "local": "Pachuca",
      "local_id": "7848",
      "visitante": "FC Juarez",
      "visitante_id": "649424",
      "goles_local": 3,
      "goles_visit": 2,
      "score": "3 - 2",
      "terminado": true
    },
    {
      "id": "4384421",
      "fecha": "2024-03-03T01:05:00Z",
      "jornada": "10",
      "local": "Cruz Azul",
      "local_id": "6578",
      "visitante": "Chivas",
      "visitante_id": "7807",
      "goles_local": 3,
      "goles_visit": 0,
      "score": "3 - 0",
      "terminado": true
    },
    {
      "id": "4384422",
      "fecha": "2024-03-03T03:10:00Z",
      "jornada": "10",
      "local": "Atlas",
      "local_id": "6577",
      "visitante": "CF America",
      "visitante_id": "6576",
      "goles_local": 1,
      "goles_visit": 5,
      "score": "1 - 5",
      "terminado": true
    },
    {
      "id": "4384423",
      "fecha": "2024-03-04T01:00:00Z",
      "jornada": "10",
      "local": "Monterrey",
      "local_id": "7849",
      "visitante": "Pumas",
      "visitante_id": "1946",
      "goles_local": 3,
      "goles_visit": 0,
      "score": "3 - 0",
      "terminado": true
    },
    {
      "id": "4384413",
      "fecha": "2024-03-04T03:00:00Z",
      "jornada": "10",
      "local": "Tijuana",
      "local_id": "162418",
      "visitante": "Leon",
      "visitante_id": "1841",
      "goles_local": 1,
      "goles_visit": 1,
      "score": "1 - 1",
      "terminado": true
    },
    {
      "id": "4384425",
      "fecha": "2024-03-09T01:00:00Z",
      "jornada": "11",
      "local": "Puebla",
      "local_id": "7847",
      "visitante": "Atlas",
      "visitante_id": "6577",
      "goles_local": 2,
      "goles_visit": 2,
      "score": "2 - 2",
      "terminado": true
    },
    {
      "id": "4384427",
      "fecha": "2024-03-09T03:00:00Z",
      "jornada": "11",
      "local": "Necaxa",
      "local_id": "1842",
      "visitante": "Atletico de San Luis",
      "visitante_id": "6358",
      "goles_local": 3,
      "goles_visit": 1,
      "score": "3 - 1",
      "terminado": true
    },
    {
      "id": "4384426",
      "fecha": "2024-03-09T03:10:00Z",
      "jornada": "11",
      "local": "FC Juarez",
      "local_id": "649424",
      "visitante": "Toluca",
      "visitante_id": "6618",
      "goles_local": 1,
      "goles_visit": 1,
      "score": "1 - 1",
      "terminado": true
    },
    {
      "id": "4384428",
      "fecha": "2024-03-09T23:05:00Z",
      "jornada": "11",
      "local": "Chivas",
      "local_id": "7807",
      "visitante": "Leon",
      "visitante_id": "1841",
      "goles_local": 1,
      "goles_visit": 2,
      "score": "1 - 2",
      "terminado": true
    },
    {
      "id": "4384429",
      "fecha": "2024-03-10T01:00:00Z",
      "jornada": "11",
      "local": "Pachuca",
      "local_id": "7848",
      "visitante": "Queretaro FC",
      "visitante_id": "1943",
      "goles_local": 1,
      "goles_visit": 2,
      "score": "1 - 2",
      "terminado": true
    },
    {
      "id": "4384430",
      "fecha": "2024-03-10T01:00:00Z",
      "jornada": "11",
      "local": "Santos Laguna",
      "local_id": "7857",
      "visitante": "Cruz Azul",
      "visitante_id": "6578",
      "goles_local": 3,
      "goles_visit": 0,
      "score": "3 - 0",
      "terminado": true
    },
    {
      "id": "4384431",
      "fecha": "2024-03-10T03:00:00Z",
      "jornada": "11",
      "local": "CF America",
      "local_id": "6576",
      "visitante": "Tigres",
      "visitante_id": "8561",
      "goles_local": 2,
      "goles_visit": 0,
      "score": "2 - 0",
      "terminado": true
    },
    {
      "id": "4384432",
      "fecha": "2024-03-10T18:00:00Z",
      "jornada": "11",
      "local": "Pumas",
      "local_id": "1946",
      "visitante": "Tijuana",
      "visitante_id": "162418",
      "goles_local": 3,
      "goles_visit": 3,
      "score": "3 - 3",
      "terminado": true
    },
    {
      "id": "4384433",
      "fecha": "2024-03-11T01:00:00Z",
      "jornada": "11",
      "local": "Monterrey",
      "local_id": "7849",
      "visitante": "Mazatlan FC",
      "visitante_id": "1170234",
      "goles_local": 2,
      "goles_visit": 1,
      "score": "2 - 1",
      "terminado": true
    },
    {
      "id": "4384434",
      "fecha": "2024-03-16T01:00:00Z",
      "jornada": "12",
      "local": "Queretaro FC",
      "local_id": "1943",
      "visitante": "FC Juarez",
      "visitante_id": "649424",
      "goles_local": 1,
      "goles_visit": 0,
      "score": "1 - 0",
      "terminado": true
    },
    {
      "id": "4384466",
      "fecha": "2024-03-16T03:00:00Z",
      "jornada": "12",
      "local": "Tijuana",
      "local_id": "162418",
      "visitante": "Santos Laguna",
      "visitante_id": "7857",
      "goles_local": 2,
      "goles_visit": 2,
      "score": "2 - 2",
      "terminado": true
    },
    {
      "id": "4384475",
      "fecha": "2024-03-16T23:00:00Z",
      "jornada": "12",
      "local": "Cruz Azul",
      "local_id": "6578",
      "visitante": "Necaxa",
      "visitante_id": "1842",
      "goles_local": 1,
      "goles_visit": 2,
      "score": "1 - 2",
      "terminado": true
    },
    {
      "id": "4384474",
      "fecha": "2024-03-17T01:00:00Z",
      "jornada": "12",
      "local": "Leon",
      "local_id": "1841",
      "visitante": "Puebla",
      "visitante_id": "7847",
      "goles_local": 2,
      "goles_visit": 1,
      "score": "2 - 1",
      "terminado": true
    },
    {
      "id": "4384472",
      "fecha": "2024-03-17T01:00:00Z",
      "jornada": "12",
      "local": "Tigres",
      "local_id": "8561",
      "visitante": "Mazatlan FC",
      "visitante_id": "1170234",
      "goles_local": 5,
      "goles_visit": 1,
      "score": "5 - 1",
      "terminado": true
    },
    {
      "id": "4384471",
      "fecha": "2024-03-17T03:05:00Z",
      "jornada": "12",
      "local": "Chivas",
      "local_id": "7807",
      "visitante": "CF America",
      "visitante_id": "6576",
      "goles_local": 0,
      "goles_visit": 0,
      "score": "0 - 0",
      "terminado": true
    },
    {
      "id": "4384470",
      "fecha": "2024-03-17T23:00:00Z",
      "jornada": "12",
      "local": "Atlas",
      "local_id": "6577",
      "visitante": "Monterrey",
      "visitante_id": "7849",
      "goles_local": 1,
      "goles_visit": 2,
      "score": "1 - 2",
      "terminado": true
    },
    {
      "id": "4384469",
      "fecha": "2024-03-18T01:00:00Z",
      "jornada": "12",
      "local": "Atletico de San Luis",
      "local_id": "6358",
      "visitante": "Pachuca",
      "visitante_id": "7848",
      "goles_local": 2,
      "goles_visit": 1,
      "score": "2 - 1",
      "terminado": true
    },
    {
      "id": "4384473",
      "fecha": "2024-03-18T01:00:00Z",
      "jornada": "12",
      "local": "Toluca",
      "local_id": "6618",
      "visitante": "Pumas",
      "visitante_id": "1946",
      "goles_local": 3,
      "goles_visit": 0,
      "score": "3 - 0",
      "terminado": true
    },
    {
      "id": "4384438",
      "fecha": "2024-03-24T01:00:00Z",
      "jornada": "7",
      "local": "FC Juarez",
      "local_id": "649424",
      "visitante": "Puebla",
      "visitante_id": "7847",
      "goles_local": 4,
      "goles_visit": 3,
      "score": "4 - 3",
      "terminado": true
    },
    {
      "id": "4384468",
      "fecha": "2024-03-30T01:00:00Z",
      "jornada": "13",
      "local": "Puebla",
      "local_id": "7847",
      "visitante": "Tigres",
      "visitante_id": "8561",
      "goles_local": 2,
      "goles_visit": 3,
      "score": "2 - 3",
      "terminado": true
    },
    {
      "id": "4384456",
      "fecha": "2024-03-30T02:00:00Z",
      "jornada": "13",
      "local": "CF America",
      "local_id": "6576",
      "visitante": "Atletico de San Luis",
      "visitante_id": "6358",
      "goles_local": 2,
      "goles_visit": 1,
      "score": "2 - 1",
      "terminado": true
    },
    {
      "id": "4384467",
      "fecha": "2024-03-30T03:00:00Z",
      "jornada": "13",
      "local": "Mazatlan FC",
      "local_id": "1170234",
      "visitante": "Tijuana",
      "visitante_id": "162418",
      "goles_local": 2,
      "goles_visit": 0,
      "score": "2 - 0",
      "terminado": true
    },
    {
      "id": "4384464",
      "fecha": "2024-03-31T01:00:00Z",
      "jornada": "13",
      "local": "Monterrey",
      "local_id": "7849",
      "visitante": "Chivas",
      "visitante_id": "7807",
      "goles_local": 0,
      "goles_visit": 2,
      "score": "0 - 2",
      "terminado": true
    },
    {
      "id": "4384465",
      "fecha": "2024-03-31T01:00:00Z",
      "jornada": "13",
      "local": "Pachuca",
      "local_id": "7848",
      "visitante": "Toluca",
      "visitante_id": "6618",
      "goles_local": 2,
      "goles_visit": 3,
      "score": "2 - 3",
      "terminado": true
    },
    {
      "id": "4384463",
      "fecha": "2024-03-31T03:05:00Z",
      "jornada": "13",
      "local": "Pumas",
      "local_id": "1946",
      "visitante": "Cruz Azul",
      "visitante_id": "6578",
      "goles_local": 0,
      "goles_visit": 0,
      "score": "0 - 0",
      "terminado": true
    },
    {
      "id": "4384462",
      "fecha": "2024-03-31T23:00:00Z",
      "jornada": "13",
      "local": "Atlas",
      "local_id": "6577",
      "visitante": "Queretaro FC",
      "visitante_id": "1943",
      "goles_local": 2,
      "goles_visit": 3,
      "score": "2 - 3",
      "terminado": true
    },
    {
      "id": "4384461",
      "fecha": "2024-04-01T01:00:00Z",
      "jornada": "13",
      "local": "Necaxa",
      "local_id": "1842",
      "visitante": "Leon",
      "visitante_id": "1841",
      "goles_local": 1,
      "goles_visit": 2,
      "score": "1 - 2",
      "terminado": true
    },
    {
      "id": "4384460",
      "fecha": "2024-04-01T01:36:00Z",
      "jornada": "13",
      "local": "FC Juarez",
      "local_id": "649424",
      "visitante": "Santos Laguna",
      "visitante_id": "7857",
      "goles_local": 2,
      "goles_visit": 1,
      "score": "2 - 1",
      "terminado": true
    },
    {
      "id": "4384459",
      "fecha": "2024-04-06T01:00:00Z",
      "jornada": "14",
      "local": "Mazatlan FC",
      "local_id": "1170234",
      "visitante": "Pumas",
      "visitante_id": "1946",
      "goles_local": 0,
      "goles_visit": 4,
      "score": "0 - 4",
      "terminado": true
    },
    {
      "id": "4384458",
      "fecha": "2024-04-06T03:10:00Z",
      "jornada": "14",
      "local": "Tijuana",
      "local_id": "162418",
      "visitante": "Necaxa",
      "visitante_id": "1842",
      "goles_local": 2,
      "goles_visit": 3,
      "score": "2 - 3",
      "terminado": true
    },
    {
      "id": "4384457",
      "fecha": "2024-04-06T23:00:00Z",
      "jornada": "14",
      "local": "Leon",
      "local_id": "1841",
      "visitante": "Queretaro FC",
      "visitante_id": "1943",
      "goles_local": 0,
      "goles_visit": 2,
      "score": "0 - 2",
      "terminado": true
    },
    {
      "id": "4384498",
      "fecha": "2024-04-07T01:00:00Z",
      "jornada": "14",
      "local": "Tigres",
      "local_id": "8561",
      "visitante": "Pachuca",
      "visitante_id": "7848",
      "goles_local": 0,
      "goles_visit": 3,
      "score": "0 - 3",
      "terminado": true
    },
    {
      "id": "4384488",
      "fecha": "2024-04-07T01:05:00Z",
      "jornada": "14",
      "local": "Chivas",
      "local_id": "7807",
      "visitante": "Puebla",
      "visitante_id": "7847",
      "goles_local": 3,
      "goles_visit": 2,
      "score": "3 - 2",
      "terminado": true
    },
    {
      "id": "4384497",
      "fecha": "2024-04-07T03:05:00Z",
      "jornada": "14",
      "local": "Cruz Azul",
      "local_id": "6578",
      "visitante": "Monterrey",
      "visitante_id": "7849",
      "goles_local": 2,
      "goles_visit": 1,
      "score": "2 - 1",
      "terminado": true
    },
    {
      "id": "4384496",
      "fecha": "2024-04-07T03:05:00Z",
      "jornada": "14",
      "local": "Santos Laguna",
      "local_id": "7857",
      "visitante": "CF America",
      "visitante_id": "6576",
      "goles_local": 1,
      "goles_visit": 1,
      "score": "1 - 1",
      "terminado": true
    },
    {
      "id": "4384495",
      "fecha": "2024-04-07T18:00:00Z",
      "jornada": "14",
      "local": "Toluca",
      "local_id": "6618",
      "visitante": "Atlas",
      "visitante_id": "6577",
      "goles_local": 4,
      "goles_visit": 1,
      "score": "4 - 1",
      "terminado": true
    },
    {
      "id": "4384494",
      "fecha": "2024-04-08T15:30:00Z",
      "jornada": "14",
      "local": "Atletico de San Luis",
      "local_id": "6358",
      "visitante": "FC Juarez",
      "visitante_id": "649424",
      "goles_local": 2,
      "goles_visit": 3,
      "score": "2 - 3",
      "terminado": true
    },
    {
      "id": "4384493",
      "fecha": "2024-04-13T01:06:00Z",
      "jornada": "15",
      "local": "Queretaro FC",
      "local_id": "1943",
      "visitante": "Mazatlan FC",
      "visitante_id": "1170234",
      "goles_local": 0,
      "goles_visit": 2,
      "score": "0 - 2",
      "terminado": true
    },
    {
      "id": "4384492",
      "fecha": "2024-04-13T03:00:00Z",
      "jornada": "15",
      "local": "Necaxa",
      "local_id": "1842",
      "visitante": "Santos Laguna",
      "visitante_id": "7857",
      "goles_local": 2,
      "goles_visit": 0,
      "score": "2 - 0",
      "terminado": true
    },
    {
      "id": "4384491",
      "fecha": "2024-04-13T03:00:00Z",
      "jornada": "15",
      "local": "Puebla",
      "local_id": "7847",
      "visitante": "Cruz Azul",
      "visitante_id": "6578",
      "goles_local": 0,
      "goles_visit": 1,
      "score": "0 - 1",
      "terminado": true
    },
    {
      "id": "4384490",
      "fecha": "2024-04-13T23:00:00Z",
      "jornada": "15",
      "local": "Pachuca",
      "local_id": "7848",
      "visitante": "Chivas",
      "visitante_id": "7807",
      "goles_local": 0,
      "goles_visit": 1,
      "score": "0 - 1",
      "terminado": true
    },
    {
      "id": "4384489",
      "fecha": "2024-04-14T01:05:00Z",
      "jornada": "15",
      "local": "CF America",
      "local_id": "6576",
      "visitante": "Toluca",
      "visitante_id": "6618",
      "goles_local": 5,
      "goles_visit": 1,
      "score": "5 - 1",
      "terminado": true
    },
    {
      "id": "4384476",
      "fecha": "2024-04-14T03:10:00Z",
      "jornada": "15",
      "local": "Monterrey",
      "local_id": "7849",
      "visitante": "Tigres",
      "visitante_id": "8561",
      "goles_local": 3,
      "goles_visit": 3,
      "score": "3 - 3",
      "terminado": true
    },
    {
      "id": "4384487",
      "fecha": "2024-04-15T00:00:00Z",
      "jornada": "15",
      "local": "Atlas",
      "local_id": "6577",
      "visitante": "Atletico de San Luis",
      "visitante_id": "6358",
      "goles_local": 2,
      "goles_visit": 1,
      "score": "2 - 1",
      "terminado": true
    },
    {
      "id": "4384486",
      "fecha": "2024-04-15T00:00:00Z",
      "jornada": "15",
      "local": "Pumas",
      "local_id": "1946",
      "visitante": "Leon",
      "visitante_id": "1841",
      "goles_local": 1,
      "goles_visit": 0,
      "score": "1 - 0",
      "terminado": true
    },
    {
      "id": "4384485",
      "fecha": "2024-04-15T02:06:00Z",
      "jornada": "15",
      "local": "FC Juarez",
      "local_id": "649424",
      "visitante": "Tijuana",
      "visitante_id": "162418",
      "goles_local": 0,
      "goles_visit": 1,
      "score": "0 - 1",
      "terminado": true
    },
    {
      "id": "4384484",
      "fecha": "2024-04-20T01:00:00Z",
      "jornada": "16",
      "local": "Mazatlan FC",
      "local_id": "1170234",
      "visitante": "FC Juarez",
      "visitante_id": "649424",
      "goles_local": 0,
      "goles_visit": 2,
      "score": "0 - 2",
      "terminado": true
    },
    {
      "id": "4384483",
      "fecha": "2024-04-20T03:00:00Z",
      "jornada": "16",
      "local": "Atletico de San Luis",
      "local_id": "6358",
      "visitante": "Toluca",
      "visitante_id": "6618",
      "goles_local": 1,
      "goles_visit": 5,
      "score": "1 - 5",
      "terminado": true
    },
    {
      "id": "4384482",
      "fecha": "2024-04-20T03:10:00Z",
      "jornada": "16",
      "local": "Tijuana",
      "local_id": "162418",
      "visitante": "Puebla",
      "visitante_id": "7847",
      "goles_local": 3,
      "goles_visit": 1,
      "score": "3 - 1",
      "terminado": true
    },
    {
      "id": "4384481",
      "fecha": "2024-04-20T23:00:00Z",
      "jornada": "16",
      "local": "Leon",
      "local_id": "1841",
      "visitante": "Monterrey",
      "visitante_id": "7849",
      "goles_local": 2,
      "goles_visit": 0,
      "score": "2 - 0",
      "terminado": true
    },
    {
      "id": "4384479",
      "fecha": "2024-04-21T01:05:00Z",
      "jornada": "16",
      "local": "Chivas",
      "local_id": "7807",
      "visitante": "Queretaro FC",
      "visitante_id": "1943",
      "goles_local": 2,
      "goles_visit": 0,
      "score": "2 - 0",
      "terminado": true
    },
    {
      "id": "4384499",
      "fecha": "2024-04-21T01:05:00Z",
      "jornada": "16",
      "local": "Santos Laguna",
      "local_id": "7857",
      "visitante": "Pachuca",
      "visitante_id": "7848",
      "goles_local": 0,
      "goles_visit": 2,
      "score": "0 - 2",
      "terminado": true
    },
    {
      "id": "4384480",
      "fecha": "2024-04-21T01:05:00Z",
      "jornada": "16",
      "local": "Tigres",
      "local_id": "8561",
      "visitante": "Necaxa",
      "visitante_id": "1842",
      "goles_local": 5,
      "goles_visit": 2,
      "score": "5 - 2",
      "terminado": true
    },
    {
      "id": "4384478",
      "fecha": "2024-04-21T03:10:00Z",
      "jornada": "16",
      "local": "Pumas",
      "local_id": "1946",
      "visitante": "CF America",
      "visitante_id": "6576",
      "goles_local": 2,
      "goles_visit": 1,
      "score": "2 - 1",
      "terminado": true
    },
    {
      "id": "4384477",
      "fecha": "2024-04-22T00:00:00Z",
      "jornada": "16",
      "local": "Cruz Azul",
      "local_id": "6578",
      "visitante": "Atlas",
      "visitante_id": "6577",
      "goles_local": 2,
      "goles_visit": 2,
      "score": "2 - 2",
      "terminado": true
    },
    {
      "id": "4384500",
      "fecha": "2024-04-27T01:00:00Z",
      "jornada": "17",
      "local": "Puebla",
      "local_id": "7847",
      "visitante": "CF America",
      "visitante_id": "6576",
      "goles_local": 1,
      "goles_visit": 2,
      "score": "1 - 2",
      "terminado": true
    },
    {
      "id": "4384501",
      "fecha": "2024-04-27T03:10:00Z",
      "jornada": "17",
      "local": "Queretaro FC",
      "local_id": "1943",
      "visitante": "Pumas",
      "visitante_id": "1946",
      "goles_local": 1,
      "goles_visit": 1,
      "score": "1 - 1",
      "terminado": true
    },
    {
      "id": "4384502",
      "fecha": "2024-04-27T23:06:00Z",
      "jornada": "17",
      "local": "FC Juarez",
      "local_id": "649424",
      "visitante": "Leon",
      "visitante_id": "1841",
      "goles_local": 1,
      "goles_visit": 1,
      "score": "1 - 1",
      "terminado": true
    },
    {
      "id": "4384503",
      "fecha": "2024-04-28T01:00:00Z",
      "jornada": "17",
      "local": "Tigres",
      "local_id": "8561",
      "visitante": "Tijuana",
      "visitante_id": "162418",
      "goles_local": 4,
      "goles_visit": 1,
      "score": "4 - 1",
      "terminado": true
    },
    {
      "id": "4384505",
      "fecha": "2024-04-28T01:00:00Z",
      "jornada": "17",
      "local": "Toluca",
      "local_id": "6618",
      "visitante": "Cruz Azul",
      "visitante_id": "6578",
      "goles_local": 0,
      "goles_visit": 1,
      "score": "0 - 1",
      "terminado": true
    },
    {
      "id": "4384504",
      "fecha": "2024-04-28T01:10:00Z",
      "jornada": "17",
      "local": "Pachuca",
      "local_id": "7848",
      "visitante": "Mazatlan FC",
      "visitante_id": "1170234",
      "goles_local": 1,
      "goles_visit": 1,
      "score": "1 - 1",
      "terminado": true
    },
    {
      "id": "4384506",
      "fecha": "2024-04-28T03:10:00Z",
      "jornada": "17",
      "local": "Atlas",
      "local_id": "6577",
      "visitante": "Chivas",
      "visitante_id": "7807",
      "goles_local": 0,
      "goles_visit": 1,
      "score": "0 - 1",
      "terminado": true
    },
    {
      "id": "4384507",
      "fecha": "2024-04-29T00:00:00Z",
      "jornada": "17",
      "local": "Necaxa",
      "local_id": "1842",
      "visitante": "Monterrey",
      "visitante_id": "7849",
      "goles_local": 2,
      "goles_visit": 5,
      "score": "2 - 5",
      "terminado": true
    },
    {
      "id": "4384508",
      "fecha": "2024-04-29T00:00:00Z",
      "jornada": "17",
      "local": "Santos Laguna",
      "local_id": "7857",
      "visitante": "Atletico de San Luis",
      "visitante_id": "6358",
      "goles_local": 0,
      "goles_visit": 3,
      "score": "0 - 3",
      "terminado": true
    },
    {
      "id": "4472364",
      "fecha": "2024-05-09T01:05:00Z",
      "jornada": "1/4",
      "local": "Chivas",
      "local_id": "7807",
      "visitante": "Toluca",
      "visitante_id": "6618",
      "goles_local": 1,
      "goles_visit": 0,
      "score": "1 - 0",
      "terminado": true
    },
    {
      "id": "4474266",
      "fecha": "2024-05-09T03:16:00Z",
      "jornada": "1/4",
      "local": "Pachuca",
      "local_id": "7848",
      "visitante": "CF America",
      "visitante_id": "6576",
      "goles_local": 1,
      "goles_visit": 1,
      "score": "1 - 1",
      "terminado": true
    },
    {
      "id": "4473017",
      "fecha": "2024-05-10T01:00:00Z",
      "jornada": "1/4",
      "local": "Pumas",
      "local_id": "1946",
      "visitante": "Cruz Azul",
      "visitante_id": "6578",
      "goles_local": 0,
      "goles_visit": 2,
      "score": "0 - 2",
      "terminado": true
    },
    {
      "id": "4472366",
      "fecha": "2024-05-10T03:10:00Z",
      "jornada": "1/4",
      "local": "Tigres",
      "local_id": "8561",
      "visitante": "Monterrey",
      "visitante_id": "7849",
      "goles_local": 1,
      "goles_visit": 2,
      "score": "1 - 2",
      "terminado": true
    },
    {
      "id": "4474234",
      "fecha": "2024-05-12T00:00:00Z",
      "jornada": "1/4",
      "local": "CF America",
      "local_id": "6576",
      "visitante": "Pachuca",
      "visitante_id": "7848",
      "goles_local": 1,
      "goles_visit": 1,
      "score": "1 - 1",
      "terminado": true
    },
    {
      "id": "4472365",
      "fecha": "2024-05-12T02:10:00Z",
      "jornada": "1/4",
      "local": "Toluca",
      "local_id": "6618",
      "visitante": "Chivas",
      "visitante_id": "7807",
      "goles_local": 0,
      "goles_visit": 0,
      "score": "0 - 0",
      "terminado": true
    },
    {
      "id": "4473018",
      "fecha": "2024-05-13T01:00:00Z",
      "jornada": "1/4",
      "local": "Cruz Azul",
      "local_id": "6578",
      "visitante": "Pumas",
      "visitante_id": "1946",
      "goles_local": 2,
      "goles_visit": 2,
      "score": "2 - 2",
      "terminado": true
    },
    {
      "id": "4472367",
      "fecha": "2024-05-13T03:10:00Z",
      "jornada": "1/4",
      "local": "Monterrey",
      "local_id": "7849",
      "visitante": "Tigres",
      "visitante_id": "8561",
      "goles_local": 1,
      "goles_visit": 1,
      "score": "1 - 1",
      "terminado": true
    },
    {
      "id": "4478402",
      "fecha": "2024-05-16T02:05:00Z",
      "jornada": "1/2",
      "local": "Chivas",
      "local_id": "7807",
      "visitante": "CF America",
      "visitante_id": "6576",
      "goles_local": 0,
      "goles_visit": 0,
      "score": "0 - 0",
      "terminado": true
    },
    {
      "id": "4478401",
      "fecha": "2024-05-17T03:00:00Z",
      "jornada": "1/2",
      "local": "Monterrey",
      "local_id": "7849",
      "visitante": "Cruz Azul",
      "visitante_id": "6578",
      "goles_local": 0,
      "goles_visit": 1,
      "score": "0 - 1",
      "terminado": true
    },
    {
      "id": "4478399",
      "fecha": "2024-05-19T02:00:00Z",
      "jornada": "1/2",
      "local": "CF America",
      "local_id": "6576",
      "visitante": "Chivas",
      "visitante_id": "7807",
      "goles_local": 1,
      "goles_visit": 0,
      "score": "1 - 0",
      "terminado": true
    },
    {
      "id": "4478400",
      "fecha": "2024-05-20T00:00:00Z",
      "jornada": "1/2",
      "local": "Cruz Azul",
      "local_id": "6578",
      "visitante": "Monterrey",
      "visitante_id": "7849",
      "goles_local": 1,
      "goles_visit": 2,
      "score": "1 - 2",
      "terminado": true
    },
    {
      "id": "4481159",
      "fecha": "2024-05-24T02:00:00Z",
      "jornada": "final",
      "local": "Cruz Azul",
      "local_id": "6578",
      "visitante": "CF America",
      "visitante_id": "6576",
      "goles_local": 1,
      "goles_visit": 1,
      "score": "1 - 1",
      "terminado": true
    },
    {
      "id": "4481156",
      "fecha": "2024-05-27T01:00:00Z",
      "jornada": "final",
      "local": "CF America",
      "local_id": "6576",
      "visitante": "Cruz Azul",
      "visitante_id": "6578",
      "goles_local": 1,
      "goles_visit": 0,
      "score": "1 - 0",
      "terminado": true
    }
  ]
}